focustools/__init__.py
focustools/util.py
focustools-0.2.3.data/scripts/focus.ctf
focustools-0.2.3.data/scripts/focus.mrcz
focustools-0.2.3.data/scripts/focus.postprocess
focustools-0.2.3.data/scripts/focus.project
focustools-0.2.3.data/scripts/focus.resample
focustools-0.2.3.dist-info/AUTHORS.md
focustools-0.2.3.dist-info/LICENSE
focustools-0.2.3.dist-info/METADATA
focustools-0.2.3.dist-info/WHEEL
focustools-0.2.3.dist-info/top_level.txt
focustools-0.2.3.dist-info/RECORD
