Metadata-Version: 2.1
Name: focustools
Version: 0.2.3
Summary: Python utilities supporting the FOCUS package and cryo-EM data processing in general.
Home-page: https://github.com/C-CINA/focustools
Author: Ricardo Righetto
Author-email: ricardo.righetto@unibas.ch
License: GPLv3
Keywords: cryoEM cryo-EM focus single-particle tomography subtomogram-averaging electron-microscopy
Platform: UNKNOWN
Requires-Dist: numpy (>=1.11)
Requires-Dist: numexpr
Requires-Dist: matplotlib
Requires-Dist: mrcz (>=0.5.3)
Requires-Dist: packaging
Requires-Dist: blosc
